submanager/__init__.py
submanager/__main__.py
submanager/cli.py
submanager/constants.py
submanager/enums.py
submanager/exceptions.py
submanager/py.typed
submanager/submanager.service
submanager/types.py
submanager/config/__init__.py
submanager/config/dynamic.py
submanager/config/lock.py
submanager/config/static.py
submanager/config/utils.py
submanager/core/__init__.py
submanager/core/commands.py
submanager/core/initialization.py
submanager/core/run.py
submanager/endpoint/__init__.py
submanager/endpoint/base.py
submanager/endpoint/creation.py
submanager/endpoint/endpoints.py
submanager/models/__init__.py
submanager/models/base.py
submanager/models/config.py
submanager/models/example.py
submanager/models/types.py
submanager/models/utils.py
submanager/sync/__init__.py
submanager/sync/manager.py
submanager/sync/menu.py
submanager/sync/processing.py
submanager/sync/utils.py
submanager/thread/__init__.py
submanager/thread/creation.py
submanager/thread/manager.py
submanager/thread/sync.py
submanager/thread/utils.py
submanager/utils/__init__.py
submanager/utils/dicthelpers.py
submanager/utils/misc.py
submanager/utils/output.py
submanager/validation/__init__.py
submanager/validation/accounts.py
submanager/validation/connection.py
submanager/validation/endpoints.py
submanager/validation/offline.py
submanager/validation/validate.py
submanager-0.6.0.dist-info/LICENSE.txt
submanager-0.6.0.dist-info/METADATA
submanager-0.6.0.dist-info/WHEEL
submanager-0.6.0.dist-info/entry_points.txt
submanager-0.6.0.dist-info/top_level.txt
submanager-0.6.0.dist-info/RECORD
