Metadata-Version: 2.1
Name: submanager
Version: 0.6.0
Summary: A bot framework for Reddit to manage threads, wiki pages, widgets, menus and more.
Home-page: https://github.com/r-spacex/submanager
Author: C.A.M. Gerlach and r/SpaceX
Author-email: CAM.Gerlach@rSpaceX.com
License: MIT
Project-URL: Github, https://github.com/r-spacex/submanager
Project-URL: Bug Tracker, https://github.com/r-spacex/submanager/issues
Project-URL: Demo, https://www.reddit.com/r/SpaceX
Keywords: reddit api praw spacex bot subreddit mod moderator
Platform: UNKNOWN
Classifier: Development Status :: 3 - Alpha
Classifier: Environment :: Console
Classifier: Environment :: No Input/Output (Daemon)
Classifier: Environment :: Web Environment
Classifier: Intended Audience :: Developers
Classifier: Intended Audience :: End Users/Desktop
Classifier: Intended Audience :: Information Technology
Classifier: Intended Audience :: System Administrators
Classifier: License :: OSI Approved :: MIT License
Classifier: Operating System :: OS Independent
Classifier: Programming Language :: Python :: 3
Classifier: Programming Language :: Python :: 3 :: Only
Classifier: Programming Language :: Python :: 3.7
Classifier: Programming Language :: Python :: 3.8
Classifier: Programming Language :: Python :: 3.9
Classifier: Topic :: Communications
Classifier: Topic :: Internet :: WWW/HTTP
Classifier: Topic :: Software Development :: Libraries :: Python Modules
Classifier: Topic :: System :: Monitoring
Classifier: Topic :: Text Processing :: Markup :: Markdown
Classifier: Topic :: Utilities
Classifier: Typing :: Typed
Requires-Python: >=3.7
License-File: LICENSE.txt
Requires-Dist: platformdirs (<3.0,>=2.2.0)
Requires-Dist: praw (<8.0,>=7.3.0)
Requires-Dist: pydantic (<2.0,>=1.8.0)
Requires-Dist: python-dateutil (<3.0,>=2.8.0)
Requires-Dist: requests (<3.0,>=2.23.0)
Requires-Dist: toml (<1.0,>=0.10.2)
Requires-Dist: typing-extensions (>=3.7.4.3)
Provides-Extra: lint
Requires-Dist: mypy (<1.0,>=0.900) ; extra == 'lint'
Requires-Dist: pre-commit (<3.0,>=2.10.0) ; extra == 'lint'
Requires-Dist: pyanalyze (<0.4,>=0.3.1) ; extra == 'lint'
Requires-Dist: pylint (<2.11,>=2.10.0) ; extra == 'lint'
Requires-Dist: types-python-dateutil ; extra == 'lint'
Requires-Dist: types-requests ; extra == 'lint'
Requires-Dist: types-toml ; extra == 'lint'
Provides-Extra: test
Requires-Dist: packaging (>=20.0) ; extra == 'test'
Requires-Dist: pytest (<7.0,>=6.2.0) ; extra == 'test'
